[{"id":"Q1634815","name":"Nordlandsbanen","length":729,"photo":"https://commons.wikimedia.org/wiki/Special:FilePath/NSB%20Di%204%20Saltfjell.jpg?width=1024"},{"id":"Q1577458","name":"Sørlandsbanen","length":549,"photo":"https://commons.wikimedia.org/wiki/Special:FilePath/NelaugStasjonOkt2021.jpg?width=1024"},{"id":"Q1253001","name":"Dovrebanen","length":485,"photo":"https://commons.wikimedia.org/wiki/Special:FilePath/Dovrebanen%20nordover%20ved%20Kvam.JPG?width=1024"},{"id":"Q1968118","name":"Rørosbanen","length":431,"photo":"https://commons.wikimedia.org/wiki/Special:FilePath/Roeros%20railway%20station.jpg?width=1024"},{"id":"Q777060","name":"Bergensbanen","length":371,"photo":"https://commons.wikimedia.org/wiki/Special:FilePath/NSB%20El%2018%202245%20Tunga.jpg?width=1024"},{"id":"Q130237187","name":"Grong–Mosjøen","length":187},{"id":"Q218805","name":"Østfoldbanen","length":170,"photo":"https://commons.wikimedia.org/wiki/Special:FilePath/MossTrainStation.JPG?width=1024"},{"id":"Q1246915","name":"Vestfoldbanen","length":148,"photo":"https://commons.wikimedia.org/wiki/Special:FilePath/70-11%20T%C3%B8nsberg%20%287957549034%29.jpg?width=1024"},{"id":"Q198769","name":"Gjøvikbanen","length":124,"photo":"https://commons.wikimedia.org/wiki/Special:FilePath/Gjoevik%20Railway%20Station.jpg?width=1024"},{"id":"Q167626","name":"Kongsvingerbanen","length":115,"photo":"https://commons.wikimedia.org/wiki/Special:FilePath/Haga%20stasjon%20TRS.jpg?width=1024"},{"id":"Q402345","name":"Raumabanen","length":114,"photo":"https://commons.wikimedia.org/wiki/Special:FilePath/Kyllingbro-05-2007.jpg?width=1024"},{"id":"Q512662","name":"Meråkerbanen","length":102,"photo":"https://commons.wikimedia.org/wiki/Special:FilePath/E9715-5792.jpg?width=1024"},{"id":"Q133929","name":"Solørbanen","length":94,"photo":"https://commons.wikimedia.org/wiki/Special:FilePath/Braskereidfoss%20stasjon.jpg?width=1024"},{"id":"Q2452021","name":"Treungenbanen","length":91,"photo":"https://commons.wikimedia.org/wiki/Special:FilePath/B%C3%B8ilefos%20bro%202.jpg?width=1024"},{"id":"Q389245","name":"Randsfjordbanen","length":90,"photo":"https://commons.wikimedia.org/wiki/Special:FilePath/Skotselv%20stasjon%20TRS%20070429%20006.jpg?width=1024"},{"id":"Q977530","name":"Østre linje","length":81},{"id":"Q1769317","name":"Setesdalsbanen","length":78,"photo":"https://commons.wikimedia.org/wiki/Special:FilePath/Setesdalsbanen%202022.jpg?width=1024"},{"id":"Q165305","name":"Jærbanen","length":75,"photo":"https://commons.wikimedia.org/wiki/Special:FilePath/Sandnes%20station%20with%20type%2073%20train.jpg?width=1024"},{"id":"Q130219827","name":"Hell–Storlien","length":71,"photo":"https://commons.wikimedia.org/wiki/Special:FilePath/Kopper%C3%A5%20stasjon%2001.jpg?width=1024"},{"id":"Q798539","name":"Hovedbanen","length":68,"photo":"https://commons.wikimedia.org/wiki/Special:FilePath/Dal%20stasjon.jpg?width=1024"},{"id":"Q980395","name":"Gardermobanen","length":64,"photo":"https://commons.wikimedia.org/wiki/Special:FilePath/Flytoget%20%285786964068%29.jpg?width=1024"},{"id":"Q130241857","name":"Dunderland–Lønsdal","length":59},{"id":"Q130243565","name":"Fauske–Bodø","length":55},{"id":"Q4589867","name":"Namsosbanen","length":51,"photo":"https://commons.wikimedia.org/wiki/Special:FilePath/Namsosbanen1.JPG?width=1024"},{"id":"Q130235155","name":"Stjørdal–Levanger","length":49},{"id":"Q7862383","name":"Tønsberg–Eidsfossbanen","length":48,"photo":"https://commons.wikimedia.org/wiki/Special:FilePath/SundbyfossJernbanebru.JPG?width=1024"},{"id":"Q2631686","name":"Bratsbergbanen","length":47,"photo":"https://commons.wikimedia.org/wiki/Special:FilePath/Nordagutu%20stasjon.jpeg?width=1024"},{"id":"Q1770029","name":"Numedalsbanen","length":47,"photo":"https://commons.wikimedia.org/wiki/Special:FilePath/Numedalsbanen%20bjornsrud.jpg?width=1024"},{"id":"Q1781007","name":"Tinnosbanen","length":47,"photo":"https://commons.wikimedia.org/wiki/Special:FilePath/Tinnoset%20stasjon%20kai%20jernbaneferge.jpg?width=1024"},{"id":"Q130526725","name":"Eina–Dokka","length":47},{"id":"Q130236625","name":"Sunnan–Snåsa","length":45},{"id":"Q1082916","name":"Ofotbanen","length":43,"photo":"https://commons.wikimedia.org/wiki/Special:FilePath/LKAB%20Dm3%201219.jpg?width=1024"},{"id":"Q1255744","name":"Drammenbanen","length":42,"photo":"https://commons.wikimedia.org/wiki/Special:FilePath/Lier%C3%A5sen%20railway%20Tunnel%20TRS%20070330%20020.jpg?width=1024"},{"id":"Q130237189","name":"Mosjøen–Elsfjord","length":42},{"id":"Q130235157","name":"Verdal–Sunnan","length":40},{"id":"Q130243564","name":"Røkland–Fauske","length":40},{"id":"Q11973815","name":"Hamar-Grundsetbanen","length":38,"photo":"https://commons.wikimedia.org/wiki/Special:FilePath/Elverum1stasjon.jpg?width=1024"},{"id":"Q130236626","name":"Snåsa–Grong","length":38},{"id":"Q195832","name":"Arendalsbanen","length":37,"photo":"https://commons.wikimedia.org/wiki/Special:FilePath/Arendal%20Jernbanest%2001.JPG?width=1024"},{"id":"Q752014","name":"Sulitjelmabanen","length":36,"photo":"https://commons.wikimedia.org/wiki/Special:FilePath/Sulitjelmabanen%20at%20Sulitjelma.jpg?width=1024"},{"id":"Q10508685","name":"Grensebanen","length":36},{"id":"Q130243563","name":"Lønsdal–Røkland","length":32},{"id":"Q1133640","name":"Roa–Hønefossbanen","length":32,"photo":"https://commons.wikimedia.org/wiki/Special:FilePath/Roa%E2%80%93H%C3%B8nefossbanen%20and%20Randsfjorden%203.jpg?width=1024"},{"id":"Q130219825","name":"Trondheim–Hell","length":32,"photo":"https://commons.wikimedia.org/wiki/Special:FilePath/E9715-5792.jpg?width=1024"},{"id":"Q130526726","name":"Dokka–Tonsåsen","length":31},{"id":"Q130237191","name":"Bjerka–Mo i Rana","length":29},{"id":"Q1770686","name":"Hardangerbana","length":28,"photo":"https://commons.wikimedia.org/wiki/Special:FilePath/Type%2064%20at%20Granvin.jpeg?width=1024"},{"id":"Q2038354","name":"Spikkestadlinjen","length":27,"photo":"https://commons.wikimedia.org/wiki/Special:FilePath/R%C3%B8yken%20stasjon%20TRS%20070210%20050.jpg?width=1024"},{"id":"Q802843","name":"Nesttun–Osbanen","length":26},{"id":"Q649916","name":"Krøderbanen","length":26,"photo":"https://commons.wikimedia.org/wiki/Special:FilePath/Nsb%20type%207a%20ulka%20kroderbanen.jpg?width=1024"},{"id":"Q1327589","name":"Thamshavnbanen","length":25,"photo":"https://commons.wikimedia.org/wiki/Special:FilePath/Thamshavn%20stasjon%20UBT-TO-001334-24%2001%201.jpg?width=1024"},{"id":"Q4691513","name":"Holmestrand–Vittingfossbanen","length":24,"photo":"https://commons.wikimedia.org/wiki/Special:FilePath/Aluminium%20train%20Holmestrand%201.jpeg?width=1024"},{"id":"Q5314872","name":"Dunderlandsbanen","length":24,"photo":"https://commons.wikimedia.org/wiki/Special:FilePath/Dunderland%20Iron%20Ore%20Company%201936a.jpeg?width=1024"},{"id":"Q130241854","name":"Tverrånes–Storforshei","length":22},{"id":"Q1170482","name":"Grimstadbanen","length":22,"photo":"https://commons.wikimedia.org/wiki/Special:FilePath/Grimstadbanen-2.jpg?width=1024"},{"id":"Q3353565","name":"Follobanen","length":22,"photo":"https://commons.wikimedia.org/wiki/Special:FilePath/Blixtunnelen%20og%20Ro%C3%A5stunnelen%20s%C3%B8ndre%20portal%20ved%20Ski.jpg?width=1024"},{"id":"Q803083","name":"Skreiabanen","length":22,"photo":"https://commons.wikimedia.org/wiki/Special:FilePath/Kraby%20railway%20station.jpg?width=1024"},{"id":"Q130237190","name":"Elsfjord–Bjerka","length":21},{"id":"Q3180607","name":"Lierbanen","length":21,"photo":"https://commons.wikimedia.org/wiki/Special:FilePath/Lier%20gamle%20stasjon.JPG?width=1024"},{"id":"Q402957","name":"Flåmsbana","length":20,"photo":"https://commons.wikimedia.org/wiki/Special:FilePath/.00%201230%20Fl%C3%A5msbana%20und%20Bahnhof%20von%20Fl%C3%A5m%2C%20Norwegen.jpg?width=1024"},{"id":"Q130526727","name":"Tonsåsen–Aurdal","length":18},{"id":"Q1427974","name":"Flekkefjordbanen","length":17,"photo":"https://commons.wikimedia.org/wiki/Special:FilePath/Flekkefjord%20stasjon.jpeg?width=1024"},{"id":"Q1281231","name":"Askerbanen","length":17,"photo":"https://commons.wikimedia.org/wiki/Special:FilePath/B%C3%A6rumstunnelen%20-%202012-03-11%20at%2012-03-48.jpg?width=1024"},{"id":"Q4583880","name":"Lillesand–Flaksvandbanen","length":17,"photo":"https://commons.wikimedia.org/wiki/Special:FilePath/Lillesand%20panorama%20in%201902.jpg?width=1024"},{"id":"Q545998","name":"Rjukanbanen","length":16,"photo":"https://commons.wikimedia.org/wiki/Special:FilePath/Rjukanmael06.jpg?width=1024"},{"id":"Q130241856","name":"Grønfjelldal–Dunderland","length":16},{"id":"Q1771722","name":"Holmenkollbanen","length":14,"photo":"https://commons.wikimedia.org/wiki/Special:FilePath/Holmenkollbanen%20tracks.jpg?width=1024"},{"id":"Q803226","name":"Vestmarkabanen","length":14},{"id":"Q5610422","name":"Grorudbanen","length":13,"photo":"https://commons.wikimedia.org/wiki/Special:FilePath/Vestli%20stasjon%20Oslo%202009%20r%201.jpg?width=1024"},{"id":"Q130526728","name":"Aurdal–Fagernes","length":13},{"id":"Q130235156","name":"Levanger–Verdal","length":12},{"id":"Q3700570","name":"Ålgårdbanen","length":12,"photo":"https://commons.wikimedia.org/wiki/Special:FilePath/%C3%85lg%C3%A5rd%20station.jpg?width=1024"},{"id":"Q738389","name":"Brevikbanen","length":10,"photo":"https://commons.wikimedia.org/wiki/Special:FilePath/Skjelsvik04.jpg?width=1024"},{"id":"Q15222207","name":"Gråkallbanen","length":9,"photo":"https://commons.wikimedia.org/wiki/Special:FilePath/Trondheim%20Strassenbahn.jpg?width=1024"},{"id":"Q11969623","name":"Fornebubanen","length":8},{"id":"Q134186021","name":"Setesdalsbanen museumsbane","length":8,"photo":"https://commons.wikimedia.org/wiki/Special:FilePath/Setesdalsbanen%209mai2004.JPG?width=1024"},{"id":"Q802540","name":"Kirkenes–Bjørnevatnbanen","length":8},{"id":"Q4577025","name":"Solbergfossbanen","length":8,"photo":"https://commons.wikimedia.org/wiki/Special:FilePath/Solbergfossbanen%201920.jpg?width=1024"},{"id":"Q4540803","name":"Røabanen","length":8,"photo":"https://commons.wikimedia.org/wiki/Special:FilePath/I12%20062%20Bf%20R%C3%B8a%2C%20ET%203147.jpg?width=1024"},{"id":"Q76281","name":"Loenga–Alnabrulinjen","length":7,"photo":"https://commons.wikimedia.org/wiki/Special:FilePath/Swedish%20train%20in%20Norway.jpg?width=1024"},{"id":"Q803227","name":"Hortenlinjen","length":7,"photo":"https://commons.wikimedia.org/wiki/Special:FilePath/Skoppum%20stasjon.jpg?width=1024"},{"id":"Q604314","name":"Røykenvikbanen","length":7,"photo":"https://commons.wikimedia.org/wiki/Special:FilePath/R%C3%B8ykenvik%20stasjon%20URN%20NBN%20no-nb%20digifoto%2020171229%2000024%20NB%20NS%20NM%2006470GU2.jpg?width=1024"},{"id":"Q11960706","name":"Bergerlinna","length":6},{"id":"Q177703","name":"Stavne–Leangenbanen","length":6,"photo":"https://commons.wikimedia.org/wiki/Special:FilePath/Entrance%20to%20Tyholt%20Tunnel%20from%20Lerkendal.jpg?width=1024"},{"id":"Q11973632","name":"Hafslundbanen","length":6,"photo":"https://commons.wikimedia.org/wiki/Special:FilePath/Hafslundbanen%20at%20Hafslund%20karbidfabrikk.jpeg?width=1024"},{"id":"Q130241855","name":"Storforshei–Grønfjelldal","length":4},{"id":"Q206259","name":"Skøyen–Filipstadlinjen","length":3,"photo":"https://commons.wikimedia.org/wiki/Special:FilePath/Filipstad%20jernbaneg%C3%A5rd.jpg?width=1024"},{"id":"Q130235154","name":"Hell–Stjørdal","length":3},{"id":"Q130241853","name":"Mo i Rana–Tverrånes","length":3},{"id":"Q1349822","name":"Havnebanen","length":2,"photo":"https://commons.wikimedia.org/wiki/Special:FilePath/Tunnels%20Oslo%20Port%20Line.jpg?width=1024"},{"id":"Q802146","name":"Dalane–Suldallinjen","length":1},{"id":"Q6950007","name":"Mågelibanen","length":1,"photo":"https://commons.wikimedia.org/wiki/Special:FilePath/M%C3%A5gelibanen%20Topp.jpg?width=1024"},{"id":"Q117767","name":"Fløibanen","length":1,"photo":"https://commons.wikimedia.org/wiki/Special:FilePath/%22Die%20einzige%20Standseilbahn%20Norwegens%22.%2001.jpg?width=1024"}]